MANIFEST.in
README.rst
setup.py
riemann_wrapper/__init__.py
riemann_wrapper.egg-info/PKG-INFO
riemann_wrapper.egg-info/SOURCES.txt
riemann_wrapper.egg-info/dependency_links.txt
riemann_wrapper.egg-info/not-zip-safe
riemann_wrapper.egg-info/requires.txt
riemann_wrapper.egg-info/top_level.txt