Metadata-Version: 1.1
Name: riemann-wrapper
Version: 0.5.6
Summary: send timing and exception stats to riemann
Home-page: https://github.com/exoscale/python-riemann-wrapper
Author: Pierre-Yves Ritschard
Author-email: pierre-yves.ritschard@exoscale.ch
License: MIT, see LICENSE file
Platform: UNKNOWN
Classifier: Development Status :: 5 - Production/Stable
Classifier: Intended Audience :: Developers
Classifier: License :: OSI Approved :: MIT License
Classifier: Natural Language :: English
Classifier: Programming Language :: Python
Classifier: Programming Language :: Python :: 3
